fishfish/__init__.py
fishfish_gg-0.1.0.dist-info/LICENSE
fishfish_gg-0.1.0.dist-info/WHEEL
fishfish_gg-0.1.0.dist-info/METADATA
fishfish_gg-0.1.0.dist-info/RECORD
