Metadata-Version: 2.1
Name: fishfish-gg
Version: 0.1.0
Summary: FishFish API library for Python
Home-page: https://fishfish.gg
License: MIT
Keywords: api,fishfish,phishing,discord
Author: fishfish-gg
Author-email: admin@fishfish.gg
Requires-Python: >=3.8,<4.0
Classifier: License :: OSI Approved :: MIT License
Classifier: Programming Language :: Python :: 3
Classifier: Programming Language :: Python :: 3.10
Classifier: Programming Language :: Python :: 3.8
Classifier: Programming Language :: Python :: 3.9
Requires-Dist: aiohttp (>=3.8.3,<4.0.0)
Requires-Dist: requests (>=2.28.1,<3.0.0)
Project-URL: Documentation, https://fishfish-py.rtfd.io
Project-URL: Repository, https://github.com/fishfish-gg/fishfish-py
